<?xml version="1.0" encoding="UTF-8"?>
<flow id="7d821dbd-79e9-428c-9500-d2099bf1d55c">
  <descriptionCdata><![CDATA[7d821dbd-79e9-428c-9500-d2099bf1d55c.baef03e0-682f-4452-bb94-2ef8e3d4a3f9.description=1f823a6e-4f1c-4a8e-9f18-0cfac408cde9.6081d646-8333-464f-83dc-2d074cd7032f.description
]]></descriptionCdata>
  <annotation></annotation>
  <name>Azure - Get Information about VM</name>
  <categories/>
  <inputs>
    <userInputBinding id="9ffefea8-a594-4174-b0e5-de1f748e44fd">
      <annotation></annotation>
      <assignFromContext>true</assignFromContext>
      <assignToContext>true</assignToContext>
      <inputType>STRING</inputType>
      <isList>false</isList>
      <required>true</required>
      <isPersisted>true</isPersisted>
      <inputSymbol>subscriptionId</inputSymbol>
      <listDelimiter>,</listDelimiter>
      <record>false</record>
      <prompt></prompt>
      <isMultiSelect>false</isMultiSelect>
      <sourceDelimiter>|</sourceDelimiter>
    </userInputBinding>
    <userInputBinding id="01306298-9e35-41e9-b33d-e6788de55958">
      <annotation></annotation>
      <assignFromContext>true</assignFromContext>
      <assignToContext>true</assignToContext>
      <inputType>STRING</inputType>
      <isList>false</isList>
      <required>false</required>
      <isPersisted>true</isPersisted>
      <inputSymbol>vmName</inputSymbol>
      <listDelimiter>,</listDelimiter>
      <record>false</record>
      <prompt></prompt>
      <isMultiSelect>false</isMultiSelect>
      <sourceDelimiter>|</sourceDelimiter>
    </userInputBinding>
    <staticBinding id="37b1b46e-ef55-4d01-a027-2eb04b2cb8a0">
      <annotation></annotation>
      <assignFromContext>true</assignFromContext>
      <assignToContext>false</assignToContext>
      <inputType>STRING</inputType>
      <isList>false</isList>
      <required>false</required>
      <isPersisted>true</isPersisted>
      <inputSymbol>proxyHost</inputSymbol>
      <listDelimiter>,</listDelimiter>
      <value></value>
      <record>false</record>
    </staticBinding>
    <staticBinding id="ed231b63-4933-4063-80ba-18350a4faee6">
      <annotation></annotation>
      <assignFromContext>true</assignFromContext>
      <assignToContext>false</assignToContext>
      <inputType>STRING</inputType>
      <isList>false</isList>
      <required>false</required>
      <isPersisted>true</isPersisted>
      <inputSymbol>proxyPort</inputSymbol>
      <listDelimiter>,</listDelimiter>
      <value></value>
      <record>false</record>
    </staticBinding>
    <staticBinding id="7f9497f3-a294-4c47-a3b9-76fc475d744a">
      <annotation></annotation>
      <assignFromContext>true</assignFromContext>
      <assignToContext>false</assignToContext>
      <inputType>STRING</inputType>
      <isList>false</isList>
      <required>false</required>
      <isPersisted>true</isPersisted>
      <inputSymbol>proxyUsername</inputSymbol>
      <listDelimiter>,</listDelimiter>
      <value></value>
      <record>false</record>
    </staticBinding>
    <staticBinding id="94aecca7-52e5-4319-a86d-0277f509c9da">
      <annotation></annotation>
      <assignFromContext>true</assignFromContext>
      <assignToContext>false</assignToContext>
      <inputType>STRING</inputType>
      <isList>false</isList>
      <required>false</required>
      <isPersisted>true</isPersisted>
      <inputSymbol>proxyPassword</inputSymbol>
      <listDelimiter>,</listDelimiter>
      <value></value>
      <record>false</record>
    </staticBinding>
    <userInputBinding id="2f0addab-b4e1-4a4f-a141-41225373d43c">
      <annotation></annotation>
      <assignFromContext>true</assignFromContext>
      <assignToContext>true</assignToContext>
      <inputType>STRING</inputType>
      <isList>false</isList>
      <required>true</required>
      <isPersisted>true</isPersisted>
      <inputSymbol>resourceGroupName</inputSymbol>
      <listDelimiter>,</listDelimiter>
      <record>false</record>
      <prompt></prompt>
      <isMultiSelect>false</isMultiSelect>
      <sourceDelimiter>|</sourceDelimiter>
    </userInputBinding>
    <userInputBinding id="f292b396-864c-427b-b688-0230922d5309">
      <annotation></annotation>
      <assignFromContext>true</assignFromContext>
      <assignToContext>true</assignToContext>
      <inputType>STRING</inputType>
      <isList>false</isList>
      <required>true</required>
      <isPersisted>true</isPersisted>
      <inputSymbol>username</inputSymbol>
      <listDelimiter>,</listDelimiter>
      <record>false</record>
      <prompt></prompt>
      <isMultiSelect>false</isMultiSelect>
      <sourceDelimiter>|</sourceDelimiter>
    </userInputBinding>
    <userInputBinding id="97eda434-4b63-4867-8943-20ded19f49e6">
      <annotation></annotation>
      <assignFromContext>true</assignFromContext>
      <assignToContext>true</assignToContext>
      <inputType>STRING</inputType>
      <isList>false</isList>
      <required>true</required>
      <isPersisted>true</isPersisted>
      <inputSymbol>password</inputSymbol>
      <listDelimiter>,</listDelimiter>
      <record>false</record>
      <prompt></prompt>
      <isMultiSelect>false</isMultiSelect>
      <sourceDelimiter>|</sourceDelimiter>
    </userInputBinding>
    <userInputBinding id="27e55650-73bb-45b3-8c69-ebbfcea4c4b6">
      <annotation></annotation>
      <assignFromContext>true</assignFromContext>
      <assignToContext>true</assignToContext>
      <inputType>STRING</inputType>
      <isList>false</isList>
      <required>true</required>
      <isPersisted>true</isPersisted>
      <inputSymbol>filePath</inputSymbol>
      <listDelimiter>,</listDelimiter>
      <record>false</record>
      <prompt></prompt>
      <isMultiSelect>false</isMultiSelect>
      <sourceDelimiter>|</sourceDelimiter>
    </userInputBinding>
  </inputs>
  <possibleResponses>
    <opResponse id="ab2b0c6c-d63d-43cf-9629-0e662280d9c5">
      <annotation></annotation>
      <name>success</name>
      <isDefault>true</isDefault>
      <onFailure>false</onFailure>
      <type>RESOLVED</type>
      <matchRules/>
    </opResponse>
    <opResponse id="b528df5a-3c31-4ca8-a741-9220e592af31">
      <annotation></annotation>
      <name>failure</name>
      <isDefault>false</isDefault>
      <onFailure>true</onFailure>
      <type>ERROR</type>
      <matchRules/>
    </opResponse>
  </possibleResponses>
  <availableResultExpressions/>
  <resultExpression id="e4ff21ee-b651-4f61-98aa-2234ec8f8c49">
    <annotation></annotation>
    <name>FailureMessage</name>
    <fieldName>FailureMessage</fieldName>
    <sourceType>RAWRESULT</sourceType>
    <filters/>
  </resultExpression>
  <iconSpec id="3e91b3b9-6e25-48dc-92af-37b3e917f824">
    <baseIcon>flow.png</baseIcon>
    <basePath>System</basePath>
    <readOnly>false</readOnly>
    <layers/>
  </iconSpec>
  <callouts/>
  <checkPointFlow>true</checkPointFlow>
  <compatibleRuntimeContext>false</compatibleRuntimeContext>
  <historyCheckPointFlow>true</historyCheckPointFlow>
  <steps>
    <step id="4a6bebb5-5100-41e8-89b5-15745f0fbdf5">
      <annotation></annotation>
      <name>Azure Get auth token</name>
      <bounds>
        <x>77.0</x>
        <y>15.0</y>
      </bounds>
      <layer>-1</layer>
      <hideInbound>false</hideInbound>
      <iconSpec id="fd4dd035-3e53-4346-a1cf-9e567e8beaeb">
        <baseIcon>flow.png</baseIcon>
        <basePath>System</basePath>
        <readOnly>false</readOnly>
        <layers/>
      </iconSpec>
      <addResultToRunContext>false</addResultToRunContext>
      <isCriticalStep>false</isCriticalStep>
      <isNonBlocking>false</isNonBlocking>
      <isParallelStep>false</isParallelStep>
      <isSingleResponse>false</isSingleResponse>
      <recordInHistory>false</recordInHistory>
      <recordRawOutput>true</recordRawOutput>
      <recordPrimaryOutput>true</recordPrimaryOutput>
      <checkPointStep>true</checkPointStep>
      <historyCheckPointStep>true</historyCheckPointStep>
      <scriptResultStep>false</scriptResultStep>
      <userPrompt></userPrompt>
      <bindings>
        <userInputBinding id="5a68538d-6da5-4fa1-8b41-3feb639acd57">
          <annotation></annotation>
          <assignFromContext>true</assignFromContext>
          <assignToContext>true</assignToContext>
          <inputType>STRING</inputType>
          <isList>false</isList>
          <required>true</required>
          <isPersisted>true</isPersisted>
          <inputSymbol>filePath</inputSymbol>
          <listDelimiter>,</listDelimiter>
          <record>false</record>
          <prompt></prompt>
          <isMultiSelect>false</isMultiSelect>
          <sourceDelimiter>|</sourceDelimiter>
        </userInputBinding>
        <userInputBinding id="29219a35-698f-460a-b496-2e3546b52a89">
          <annotation></annotation>
          <assignFromContext>true</assignFromContext>
          <assignToContext>true</assignToContext>
          <inputType>STRING</inputType>
          <isList>false</isList>
          <required>true</required>
          <isPersisted>true</isPersisted>
          <inputSymbol>username</inputSymbol>
          <listDelimiter>,</listDelimiter>
          <record>false</record>
          <prompt></prompt>
          <isMultiSelect>false</isMultiSelect>
          <sourceDelimiter>|</sourceDelimiter>
        </userInputBinding>
        <userInputBinding id="6b1ba2f8-ce63-4b90-9634-81c4f7eeffc8">
          <annotation></annotation>
          <assignFromContext>true</assignFromContext>
          <assignToContext>true</assignToContext>
          <inputType>STRING</inputType>
          <isList>false</isList>
          <required>true</required>
          <isPersisted>true</isPersisted>
          <inputSymbol>password</inputSymbol>
          <listDelimiter>,</listDelimiter>
          <record>false</record>
          <prompt></prompt>
          <isMultiSelect>false</isMultiSelect>
          <sourceDelimiter>|</sourceDelimiter>
        </userInputBinding>
        <staticBinding id="1fb5c3c0-92d5-48ae-9e05-be824f8916e5">
          <annotation></annotation>
          <assignFromContext>true</assignFromContext>
          <assignToContext>true</assignToContext>
          <inputType>STRING</inputType>
          <isList>false</isList>
          <required>false</required>
          <isPersisted>true</isPersisted>
          <inputSymbol>proxyHost</inputSymbol>
          <listDelimiter>,</listDelimiter>
          <value></value>
          <record>false</record>
        </staticBinding>
        <staticBinding id="020735ad-ae35-4fc7-b8b6-47b457bfb203">
          <annotation></annotation>
          <assignFromContext>true</assignFromContext>
          <assignToContext>true</assignToContext>
          <inputType>STRING</inputType>
          <isList>false</isList>
          <required>false</required>
          <isPersisted>true</isPersisted>
          <inputSymbol>proxyPort</inputSymbol>
          <listDelimiter>,</listDelimiter>
          <value></value>
          <record>false</record>
        </staticBinding>
        <staticBinding id="9978b34e-360e-4414-af7b-49c4aa33aa11">
          <annotation></annotation>
          <assignFromContext>true</assignFromContext>
          <assignToContext>true</assignToContext>
          <inputType>STRING</inputType>
          <isList>false</isList>
          <required>false</required>
          <isPersisted>true</isPersisted>
          <inputSymbol>proxyUsername</inputSymbol>
          <listDelimiter>,</listDelimiter>
          <value></value>
          <record>false</record>
        </staticBinding>
        <staticBinding id="f0575cf8-7b05-4235-b365-841edca40699">
          <annotation></annotation>
          <assignFromContext>true</assignFromContext>
          <assignToContext>true</assignToContext>
          <inputType>STRING</inputType>
          <isList>false</isList>
          <required>false</required>
          <isPersisted>true</isPersisted>
          <inputSymbol>proxyPassword</inputSymbol>
          <listDelimiter>,</listDelimiter>
          <value></value>
          <record>false</record>
        </staticBinding>
      </bindings>
      <transitions>
        <transition id="7c03c840-567e-4c5f-af10-c908ac951c7c">
          <annotation></annotation>
          <name>success</name>
          <command>NEXT</command>
          <linkMode>false</linkMode>
          <responseSymbol>success</responseSymbol>
          <shouldHandoff>false</shouldHandoff>
          <transitionValue>0.0</transitionValue>
          <destination>
            <refId>13483fa9-b0c3-48b3-aea0-575fe32fbd5a</refId>
          </destination>
          <source>
            <refId>4a6bebb5-5100-41e8-89b5-15745f0fbdf5</refId>
          </source>
          <positions>
            <point>
              <x>127.0</x>
              <y>49.0</y>
            </point>
            <point>
              <x>285.0</x>
              <y>47.0</y>
            </point>
          </positions>
          <labelPosition>
            <x>333.0</x>
            <y>0.0</y>
          </labelPosition>
        </transition>
        <transition id="ea649802-bb22-48b1-b8c5-012d0bb0824e">
          <annotation></annotation>
          <name>failure</name>
          <command>NEXT</command>
          <linkMode>false</linkMode>
          <responseSymbol>failure</responseSymbol>
          <shouldHandoff>false</shouldHandoff>
          <transitionValue>0.0</transitionValue>
          <destination>
            <refId>7df66eb5-cb73-4baa-ac27-a2650c26feea</refId>
          </destination>
          <source>
            <refId>4a6bebb5-5100-41e8-89b5-15745f0fbdf5</refId>
          </source>
          <positions>
            <point>
              <x>127.0</x>
              <y>49.0</y>
            </point>
            <point>
              <x>396.0</x>
              <y>188.0</y>
            </point>
          </positions>
          <labelPosition>
            <x>333.0</x>
            <y>0.0</y>
          </labelPosition>
        </transition>
      </transitions>
      <properties/>
      <opRef>
        <refId>732a7952-7643-4321-b645-ecc04b415ab2</refId>
      </opRef>
      <assignments/>
      <throttleSize>0</throttleSize>
    </step>
    <step id="baef03e0-682f-4452-bb94-2ef8e3d4a3f9">
      <annotation>7d821dbd-79e9-428c-9500-d2099bf1d55c.baef03e0-682f-4452-bb94-2ef8e3d4a3f9.description</annotation>
      <name>Get Value from Object</name>
      <bounds>
        <x>413.0</x>
        <y>15.0</y>
      </bounds>
      <layer>-1</layer>
      <hideInbound>false</hideInbound>
      <iconSpec id="89052bf3-968e-4234-a968-fd0de710eaee">
        <baseIcon>text_code_javascript.png</baseIcon>
        <basePath>/Others/</basePath>
        <readOnly>false</readOnly>
        <layers/>
      </iconSpec>
      <addResultToRunContext>false</addResultToRunContext>
      <isCriticalStep>false</isCriticalStep>
      <isNonBlocking>false</isNonBlocking>
      <isParallelStep>false</isParallelStep>
      <isSingleResponse>false</isSingleResponse>
      <recordInHistory>false</recordInHistory>
      <recordRawOutput>true</recordRawOutput>
      <recordPrimaryOutput>true</recordPrimaryOutput>
      <checkPointStep>true</checkPointStep>
      <historyCheckPointStep>true</historyCheckPointStep>
      <scriptResultStep>false</scriptResultStep>
      <userPrompt></userPrompt>
      <bindings>
        <staticBinding id="fb1139f6-c631-40b8-8607-6243c79b6af6">
          <annotation></annotation>
          <assignFromContext>false</assignFromContext>
          <assignToContext>true</assignToContext>
          <inputType>STRING</inputType>
          <isList>false</isList>
          <required>true</required>
          <isPersisted>true</isPersisted>
          <inputSymbol>object</inputSymbol>
          <listDelimiter>,</listDelimiter>
          <value>${returnResult}</value>
          <record>false</record>
        </staticBinding>
        <staticBinding id="b6ee6f7f-8c7a-4998-8c38-82f7112b14d3">
          <annotation></annotation>
          <assignFromContext>false</assignFromContext>
          <assignToContext>true</assignToContext>
          <inputType>STRING</inputType>
          <isList>false</isList>
          <required>true</required>
          <isPersisted>true</isPersisted>
          <inputSymbol>key</inputSymbol>
          <listDelimiter>,</listDelimiter>
          <value>properties.provisioningState</value>
          <record>false</record>
        </staticBinding>
      </bindings>
      <transitions>
        <transition id="5cfa9b47-67aa-4a85-b91f-f2f0d1330086">
          <annotation></annotation>
          <name>failure</name>
          <command>NEXT</command>
          <linkMode>false</linkMode>
          <responseSymbol>failure</responseSymbol>
          <shouldHandoff>false</shouldHandoff>
          <transitionValue>0.0</transitionValue>
          <destination>
            <refId>7df66eb5-cb73-4baa-ac27-a2650c26feea</refId>
          </destination>
          <source>
            <refId>baef03e0-682f-4452-bb94-2ef8e3d4a3f9</refId>
          </source>
          <positions>
            <point>
              <x>463.0</x>
              <y>49.0</y>
            </point>
            <point>
              <x>396.0</x>
              <y>188.0</y>
            </point>
          </positions>
          <labelPosition>
            <x>333.0</x>
            <y>0.0</y>
          </labelPosition>
        </transition>
        <transition id="9a8552ae-8b1c-4ff0-ba68-33dc26840e62">
          <annotation></annotation>
          <name>success</name>
          <command>NEXT</command>
          <linkMode>false</linkMode>
          <responseSymbol>success</responseSymbol>
          <shouldHandoff>false</shouldHandoff>
          <transitionValue>0.0</transitionValue>
          <destination>
            <refId>2094b1a4-cb69-42c1-809e-71c94ee093b6</refId>
          </destination>
          <source>
            <refId>baef03e0-682f-4452-bb94-2ef8e3d4a3f9</refId>
          </source>
          <positions>
            <point>
              <x>463.0</x>
              <y>49.0</y>
            </point>
            <point>
              <x>84.0</x>
              <y>211.0</y>
            </point>
          </positions>
          <labelPosition>
            <x>333.0</x>
            <y>0.0</y>
          </labelPosition>
        </transition>
      </transitions>
      <properties/>
      <opRef>
        <refId>61fc6fd2-7d5c-4d5c-aaa9-71c8250310f2</refId>
      </opRef>
      <assignments>
        <flowVariableAssignment id="da3b138c-1a27-4705-9e8a-e73f09da6d8a">
          <annotation></annotation>
          <name>assignment</name>
          <action>OVERWRITE</action>
          <assignmentTargetType>FLOW_OUTPUT_FIELD</assignmentTargetType>
          <contextKey>state</contextKey>
          <expression id="20bc5168-f3a1-4c94-9eaf-5dfc6e7bdfb0">
            <annotation></annotation>
            <name>Result Field: Result</name>
            <fieldName>Result</fieldName>
            <sourceType>RAWRESULT</sourceType>
            <filters/>
          </expression>
        </flowVariableAssignment>
        <flowVariableAssignment id="d18b5e85-ad79-4b5a-ad3e-7f9ad5cb16b1">
          <annotation></annotation>
          <name>assignment</name>
          <action>OVERWRITE</action>
          <assignmentTargetType>FLOW_VARIABLE</assignmentTargetType>
          <contextKey>state</contextKey>
          <expression id="c506b1c6-867d-4682-94c4-1ca0396e7316">
            <annotation></annotation>
            <name>Result Field: Result</name>
            <fieldName>Result</fieldName>
            <sourceType>RAWRESULT</sourceType>
            <filters/>
          </expression>
        </flowVariableAssignment>
      </assignments>
      <throttleSize>0</throttleSize>
    </step>
    <returnStep id="2094b1a4-cb69-42c1-809e-71c94ee093b6">
      <annotation></annotation>
      <name>Resolved : success</name>
      <bounds>
        <x>532.0</x>
        <y>17.0</y>
      </bounds>
      <layer>-1</layer>
      <hideInbound>false</hideInbound>
      <addResultToRunContext>false</addResultToRunContext>
      <isCriticalStep>false</isCriticalStep>
      <isNonBlocking>false</isNonBlocking>
      <isParallelStep>false</isParallelStep>
      <isSingleResponse>false</isSingleResponse>
      <recordInHistory>false</recordInHistory>
      <recordRawOutput>true</recordRawOutput>
      <recordPrimaryOutput>true</recordPrimaryOutput>
      <checkPointStep>true</checkPointStep>
      <historyCheckPointStep>true</historyCheckPointStep>
      <scriptResultStep>false</scriptResultStep>
      <userPrompt></userPrompt>
      <bindings/>
      <transitions>
        <transition id="29d8fbe8-04d8-486e-bfa3-eb8c82434ca1">
          <annotation></annotation>
          <name>return</name>
          <command>NEXT</command>
          <linkMode>false</linkMode>
          <responseSymbol>success</responseSymbol>
          <shouldHandoff>false</shouldHandoff>
          <transitionValue>0.0</transitionValue>
          <destination>
            <refId>2094b1a4-cb69-42c1-809e-71c94ee093b6</refId>
          </destination>
          <source>
            <refId>2094b1a4-cb69-42c1-809e-71c94ee093b6</refId>
          </source>
          <positions/>
        </transition>
      </transitions>
      <properties/>
      <returnStepType>RESOLVED</returnStepType>
      <assignments/>
    </returnStep>
    <step id="13483fa9-b0c3-48b3-aea0-575fe32fbd5a">
      <annotation></annotation>
      <name>Get information about VM</name>
      <bounds>
        <x>265.0</x>
        <y>19.0</y>
      </bounds>
      <layer>-1</layer>
      <hideInbound>false</hideInbound>
      <iconSpec id="40b19c14-55d1-49fc-8233-97e47d602d3c">
        <baseIcon>flow.png</baseIcon>
        <basePath>System</basePath>
        <readOnly>false</readOnly>
        <layers/>
      </iconSpec>
      <addResultToRunContext>false</addResultToRunContext>
      <isCriticalStep>false</isCriticalStep>
      <isNonBlocking>false</isNonBlocking>
      <isParallelStep>false</isParallelStep>
      <isSingleResponse>false</isSingleResponse>
      <recordInHistory>false</recordInHistory>
      <recordRawOutput>true</recordRawOutput>
      <recordPrimaryOutput>true</recordPrimaryOutput>
      <checkPointStep>true</checkPointStep>
      <historyCheckPointStep>true</historyCheckPointStep>
      <scriptResultStep>false</scriptResultStep>
      <userPrompt></userPrompt>
      <bindings>
        <userInputBinding id="3707f8fe-b33c-4623-89b5-a70a5e6a9c76">
          <annotation></annotation>
          <assignFromContext>true</assignFromContext>
          <assignToContext>true</assignToContext>
          <inputType>STRING</inputType>
          <isList>false</isList>
          <required>true</required>
          <isPersisted>true</isPersisted>
          <inputSymbol>subscriptionId</inputSymbol>
          <listDelimiter>,</listDelimiter>
          <record>false</record>
          <prompt></prompt>
          <isMultiSelect>false</isMultiSelect>
          <sourceDelimiter>|</sourceDelimiter>
        </userInputBinding>
        <staticBinding id="5ab0e2e4-2a35-49df-9137-062c79857767">
          <annotation></annotation>
          <assignFromContext>true</assignFromContext>
          <assignToContext>true</assignToContext>
          <inputType>STRING</inputType>
          <isList>false</isList>
          <required>false</required>
          <isPersisted>true</isPersisted>
          <inputSymbol>proxyUsername</inputSymbol>
          <listDelimiter>,</listDelimiter>
          <record>false</record>
        </staticBinding>
        <staticBinding id="5b8e1607-97a5-41ca-b4c7-ce8f9a196f65">
          <annotation></annotation>
          <assignFromContext>true</assignFromContext>
          <assignToContext>true</assignToContext>
          <inputType>STRING</inputType>
          <isList>false</isList>
          <required>false</required>
          <isPersisted>true</isPersisted>
          <inputSymbol>proxyPassword</inputSymbol>
          <listDelimiter>,</listDelimiter>
          <record>false</record>
        </staticBinding>
        <staticBinding id="611c2388-fb84-4e0c-aea7-30ba519aea2d">
          <annotation></annotation>
          <assignFromContext>true</assignFromContext>
          <assignToContext>true</assignToContext>
          <inputType>STRING</inputType>
          <isList>false</isList>
          <required>false</required>
          <isPersisted>true</isPersisted>
          <inputSymbol>proxyHost</inputSymbol>
          <listDelimiter>,</listDelimiter>
          <record>false</record>
        </staticBinding>
        <staticBinding id="55a461a4-dbee-425c-a7d5-e391b9203b49">
          <annotation></annotation>
          <assignFromContext>true</assignFromContext>
          <assignToContext>true</assignToContext>
          <inputType>STRING</inputType>
          <isList>false</isList>
          <required>false</required>
          <isPersisted>true</isPersisted>
          <inputSymbol>proxyPort</inputSymbol>
          <listDelimiter>,</listDelimiter>
          <record>false</record>
        </staticBinding>
        <userInputBinding id="c273739f-264b-4ee1-8618-58b452f5b6f3">
          <annotation></annotation>
          <assignFromContext>true</assignFromContext>
          <assignToContext>true</assignToContext>
          <inputType>STRING</inputType>
          <isList>false</isList>
          <required>true</required>
          <isPersisted>true</isPersisted>
          <inputSymbol>vmName</inputSymbol>
          <listDelimiter>,</listDelimiter>
          <record>false</record>
          <prompt></prompt>
          <isMultiSelect>false</isMultiSelect>
          <sourceDelimiter>|</sourceDelimiter>
        </userInputBinding>
        <userInputBinding id="846259c8-26f3-4d50-b9e6-f181733b2149">
          <annotation></annotation>
          <assignFromContext>true</assignFromContext>
          <assignToContext>true</assignToContext>
          <inputType>STRING</inputType>
          <isList>false</isList>
          <required>true</required>
          <isPersisted>true</isPersisted>
          <inputSymbol>resourceGroupName</inputSymbol>
          <listDelimiter>,</listDelimiter>
          <record>false</record>
          <prompt></prompt>
          <isMultiSelect>false</isMultiSelect>
          <sourceDelimiter>|</sourceDelimiter>
        </userInputBinding>
        <userInputBinding id="35e334a5-5da9-4a6b-b048-56040bb4402f">
          <annotation></annotation>
          <assignFromContext>true</assignFromContext>
          <assignToContext>true</assignToContext>
          <inputType>STRING</inputType>
          <isList>false</isList>
          <required>true</required>
          <isPersisted>true</isPersisted>
          <inputSymbol>filePath</inputSymbol>
          <listDelimiter>,</listDelimiter>
          <record>false</record>
          <prompt></prompt>
          <isMultiSelect>false</isMultiSelect>
          <sourceDelimiter>|</sourceDelimiter>
        </userInputBinding>
        <userInputBinding id="d19341a7-4b70-4d98-88f7-e32e9ed07320">
          <annotation></annotation>
          <assignFromContext>true</assignFromContext>
          <assignToContext>true</assignToContext>
          <inputType>STRING</inputType>
          <isList>false</isList>
          <required>true</required>
          <isPersisted>true</isPersisted>
          <inputSymbol>username</inputSymbol>
          <listDelimiter>,</listDelimiter>
          <record>false</record>
          <prompt></prompt>
          <isMultiSelect>false</isMultiSelect>
          <sourceDelimiter>|</sourceDelimiter>
        </userInputBinding>
        <userInputBinding id="16743df4-4cba-4226-9a57-18fc3de45204">
          <annotation></annotation>
          <assignFromContext>true</assignFromContext>
          <assignToContext>true</assignToContext>
          <inputType>STRING</inputType>
          <isList>false</isList>
          <required>true</required>
          <isPersisted>true</isPersisted>
          <inputSymbol>password</inputSymbol>
          <listDelimiter>,</listDelimiter>
          <record>false</record>
          <prompt></prompt>
          <isMultiSelect>false</isMultiSelect>
          <sourceDelimiter>|</sourceDelimiter>
        </userInputBinding>
      </bindings>
      <transitions>
        <transition id="309dedb4-dd28-4a05-ae4e-412f3bbdcb8b">
          <annotation></annotation>
          <name>failure</name>
          <command>NEXT</command>
          <linkMode>false</linkMode>
          <responseSymbol>failure</responseSymbol>
          <shouldHandoff>false</shouldHandoff>
          <transitionValue>0.0</transitionValue>
          <destination>
            <refId>7df66eb5-cb73-4baa-ac27-a2650c26feea</refId>
          </destination>
          <source>
            <refId>13483fa9-b0c3-48b3-aea0-575fe32fbd5a</refId>
          </source>
          <positions>
            <point>
              <x>315.0</x>
              <y>53.0</y>
            </point>
            <point>
              <x>396.0</x>
              <y>188.0</y>
            </point>
          </positions>
          <labelPosition>
            <x>333.0</x>
            <y>0.0</y>
          </labelPosition>
        </transition>
        <transition id="17e61e9a-abe8-4389-9d20-33cc9a75fbd8">
          <annotation></annotation>
          <name>success</name>
          <command>NEXT</command>
          <linkMode>false</linkMode>
          <responseSymbol>success</responseSymbol>
          <shouldHandoff>false</shouldHandoff>
          <transitionValue>0.0</transitionValue>
          <destination>
            <refId>baef03e0-682f-4452-bb94-2ef8e3d4a3f9</refId>
          </destination>
          <source>
            <refId>13483fa9-b0c3-48b3-aea0-575fe32fbd5a</refId>
          </source>
          <positions>
            <point>
              <x>315.0</x>
              <y>53.0</y>
            </point>
            <point>
              <x>463.0</x>
              <y>49.0</y>
            </point>
          </positions>
          <labelPosition>
            <x>333.0</x>
            <y>0.0</y>
          </labelPosition>
        </transition>
      </transitions>
      <properties/>
      <opRef>
        <refId>ef21b983-2551-4af3-a49c-673a1c2c3136</refId>
      </opRef>
      <assignments>
        <flowVariableAssignment id="a5f931c2-4954-494e-ad90-81f60a1598ef">
          <annotation></annotation>
          <name>assignment</name>
          <action>OVERWRITE</action>
          <assignmentTargetType>FLOW_VARIABLE</assignmentTargetType>
          <contextKey>returnResult</contextKey>
          <expression id="d72d93a1-ce2c-4c47-b818-53c4b7f2b97f">
            <annotation></annotation>
            <name>Result Field: returnResult</name>
            <fieldName>returnResult</fieldName>
            <sourceType>RAWRESULT</sourceType>
            <filters/>
          </expression>
        </flowVariableAssignment>
      </assignments>
      <throttleSize>0</throttleSize>
    </step>
    <returnStep id="7df66eb5-cb73-4baa-ac27-a2650c26feea">
      <annotation></annotation>
      <name>Error : failure</name>
      <bounds>
        <x>264.0</x>
        <y>156.0</y>
      </bounds>
      <layer>-1</layer>
      <hideInbound>false</hideInbound>
      <addResultToRunContext>false</addResultToRunContext>
      <isCriticalStep>false</isCriticalStep>
      <isNonBlocking>false</isNonBlocking>
      <isParallelStep>false</isParallelStep>
      <isSingleResponse>false</isSingleResponse>
      <recordInHistory>false</recordInHistory>
      <recordRawOutput>true</recordRawOutput>
      <recordPrimaryOutput>true</recordPrimaryOutput>
      <checkPointStep>true</checkPointStep>
      <historyCheckPointStep>true</historyCheckPointStep>
      <scriptResultStep>false</scriptResultStep>
      <userPrompt></userPrompt>
      <bindings/>
      <transitions>
        <transition id="baf1839d-e25f-4e9a-a1b2-64d7caccb457">
          <annotation></annotation>
          <name>return</name>
          <command>NEXT</command>
          <linkMode>false</linkMode>
          <responseSymbol>failure</responseSymbol>
          <shouldHandoff>false</shouldHandoff>
          <transitionValue>0.0</transitionValue>
          <destination>
            <refId>7df66eb5-cb73-4baa-ac27-a2650c26feea</refId>
          </destination>
          <source>
            <refId>7df66eb5-cb73-4baa-ac27-a2650c26feea</refId>
          </source>
          <positions/>
        </transition>
      </transitions>
      <properties/>
      <returnStepType>ERROR</returnStepType>
      <assignments/>
    </returnStep>
  </steps>
  <startSteps>4a6bebb5-5100-41e8-89b5-15745f0fbdf5</startSteps>
</flow>