<?xml version="1.0" encoding="UTF-8"?>
<flow id="fa7a1bdd-c1fa-4188-a856-79c8a0805237">
  <descriptionCdata><![CDATA[fa7a1bdd-c1fa-4188-a856-79c8a0805237.101b404d-80bb-451f-974a-4ce0aba2b56a.prompt=Enter a value for location
fa7a1bdd-c1fa-4188-a856-79c8a0805237.2256df27-62ba-4eed-8f36-5d6ac4f4bb53.description=2384e117-b227-49a5-809e-60d9dd35f736.e920d311-1b57-4b4c-ad77-3b97d8100ca4.description
fa7a1bdd-c1fa-4188-a856-79c8a0805237.2d92f873-902d-46fd-8600-b984f816e6a5.prompt=Enter a value for resourceGroupName
fa7a1bdd-c1fa-4188-a856-79c8a0805237.319ec55e-e6b7-4d28-931c-22da297224fd.prompt=Enter a value for subscriptionId
fa7a1bdd-c1fa-4188-a856-79c8a0805237.53c46ea1-4149-4e7c-8a73-d1a2a06ffb01.prompt=Enter a value for authToken
fa7a1bdd-c1fa-4188-a856-79c8a0805237.57261b5a-f8b5-4d78-aa54-1c794d654e13.prompt=Enter a value for virtualNetworkName
fa7a1bdd-c1fa-4188-a856-79c8a0805237.615e6c48-817c-4f92-97ae-a3c180e9e8f8.prompt=Enter a value for password
fa7a1bdd-c1fa-4188-a856-79c8a0805237.a2fb8a56-43ce-4af6-b407-67cf19ac5b4c.description=1f823a6e-4f1c-4a8e-9f18-0cfac408cde9.6081d646-8333-464f-83dc-2d074cd7032f.description
fa7a1bdd-c1fa-4188-a856-79c8a0805237.a73d7279-329d-4d5d-aa92-28841ee7ba35.description=2384e117-b227-49a5-809e-60d9dd35f736.e8ea14b6-2f52-4c2b-a29d-5d748fc7951f.description
fa7a1bdd-c1fa-4188-a856-79c8a0805237.c9558c15-dcb4-4c8c-970e-dfdcf9364d25.prompt=Enter a value for username
fa7a1bdd-c1fa-4188-a856-79c8a0805237.ca1915ea-2a34-4954-adcf-ebd4df8ab32e.prompt=Enter a value for filePath
fa7a1bdd-c1fa-4188-a856-79c8a0805237.d7b9e0d1-2db9-41ef-9366-d058ed9a3a07.description=2384e117-b227-49a5-809e-60d9dd35f736.3462dbd1-9624-430c-a940-710cb4c85853.description
]]></descriptionCdata>
  <annotation></annotation>
  <name>Azure-Create virtual network</name>
  <categories/>
  <inputs>
    <userInputBinding id="ea27715b-d700-41fa-8fa5-ac6cfba4e35e">
      <annotation></annotation>
      <assignFromContext>true</assignFromContext>
      <assignToContext>true</assignToContext>
      <inputType>STRING</inputType>
      <isList>false</isList>
      <required>true</required>
      <isPersisted>true</isPersisted>
      <inputSymbol>subscriptionId</inputSymbol>
      <listDelimiter>,</listDelimiter>
      <record>false</record>
      <prompt></prompt>
      <isMultiSelect>false</isMultiSelect>
      <sourceDelimiter>|</sourceDelimiter>
    </userInputBinding>
    <staticBinding id="4e7a3055-4f46-45b8-8f24-ab78b70f7e61">
      <annotation></annotation>
      <assignFromContext>true</assignFromContext>
      <assignToContext>false</assignToContext>
      <inputType>STRING</inputType>
      <isList>false</isList>
      <required>false</required>
      <isPersisted>true</isPersisted>
      <inputSymbol>proxyHost</inputSymbol>
      <listDelimiter>,</listDelimiter>
      <value></value>
      <record>false</record>
    </staticBinding>
    <staticBinding id="7ee199bf-3879-486e-abf8-68504b2107f9">
      <annotation></annotation>
      <assignFromContext>true</assignFromContext>
      <assignToContext>false</assignToContext>
      <inputType>STRING</inputType>
      <isList>false</isList>
      <required>false</required>
      <isPersisted>true</isPersisted>
      <inputSymbol>proxyPort</inputSymbol>
      <listDelimiter>,</listDelimiter>
      <value></value>
      <record>false</record>
    </staticBinding>
    <staticBinding id="e342a711-dfe6-416a-98b8-37170b7b027e">
      <annotation></annotation>
      <assignFromContext>true</assignFromContext>
      <assignToContext>false</assignToContext>
      <inputType>STRING</inputType>
      <isList>false</isList>
      <required>false</required>
      <isPersisted>true</isPersisted>
      <inputSymbol>proxyUsername</inputSymbol>
      <listDelimiter>,</listDelimiter>
      <value></value>
      <record>false</record>
    </staticBinding>
    <staticBinding id="1ca53b67-ff51-4915-88b4-cc73331de068">
      <annotation></annotation>
      <assignFromContext>true</assignFromContext>
      <assignToContext>false</assignToContext>
      <inputType>STRING</inputType>
      <isList>false</isList>
      <required>false</required>
      <isPersisted>true</isPersisted>
      <inputSymbol>proxyPassword</inputSymbol>
      <listDelimiter>,</listDelimiter>
      <value></value>
      <record>false</record>
    </staticBinding>
    <userInputBinding id="dc9b18af-389c-4779-9965-833e51a37a43">
      <annotation></annotation>
      <assignFromContext>true</assignFromContext>
      <assignToContext>true</assignToContext>
      <inputType>STRING</inputType>
      <isList>false</isList>
      <required>true</required>
      <isPersisted>true</isPersisted>
      <inputSymbol>resourceGroupName</inputSymbol>
      <listDelimiter>,</listDelimiter>
      <record>false</record>
      <prompt></prompt>
      <isMultiSelect>false</isMultiSelect>
      <sourceDelimiter>|</sourceDelimiter>
    </userInputBinding>
    <userInputBinding id="5aafd1be-9d9e-4b10-944a-330449750015">
      <annotation></annotation>
      <assignFromContext>true</assignFromContext>
      <assignToContext>true</assignToContext>
      <inputType>STRING</inputType>
      <isList>false</isList>
      <required>true</required>
      <isPersisted>true</isPersisted>
      <inputSymbol>username</inputSymbol>
      <listDelimiter>,</listDelimiter>
      <record>false</record>
      <prompt></prompt>
      <isMultiSelect>false</isMultiSelect>
      <sourceDelimiter>|</sourceDelimiter>
    </userInputBinding>
    <userInputBinding id="9ce298a9-aa49-4263-aff8-c2f62dbe1592">
      <annotation></annotation>
      <assignFromContext>true</assignFromContext>
      <assignToContext>true</assignToContext>
      <inputType>STRING</inputType>
      <isList>false</isList>
      <required>true</required>
      <isPersisted>true</isPersisted>
      <inputSymbol>password</inputSymbol>
      <listDelimiter>,</listDelimiter>
      <record>false</record>
      <prompt></prompt>
      <isMultiSelect>false</isMultiSelect>
      <sourceDelimiter>|</sourceDelimiter>
    </userInputBinding>
    <userInputBinding id="b7434c9d-f66b-42d5-9f24-45ec55a04198">
      <annotation></annotation>
      <assignFromContext>true</assignFromContext>
      <assignToContext>true</assignToContext>
      <inputType>STRING</inputType>
      <isList>false</isList>
      <required>true</required>
      <isPersisted>true</isPersisted>
      <inputSymbol>filePath</inputSymbol>
      <listDelimiter>,</listDelimiter>
      <record>false</record>
      <prompt></prompt>
      <isMultiSelect>false</isMultiSelect>
      <sourceDelimiter>|</sourceDelimiter>
    </userInputBinding>
    <userInputBinding id="dcc48cf2-65c9-4133-a554-42bdc7f67408">
      <annotation></annotation>
      <assignFromContext>true</assignFromContext>
      <assignToContext>true</assignToContext>
      <inputType>STRING</inputType>
      <isList>false</isList>
      <required>true</required>
      <isPersisted>true</isPersisted>
      <inputSymbol>virtualNetworkName</inputSymbol>
      <listDelimiter>,</listDelimiter>
      <record>false</record>
      <prompt></prompt>
      <isMultiSelect>false</isMultiSelect>
      <sourceDelimiter>|</sourceDelimiter>
    </userInputBinding>
    <userInputBinding id="1d86f7a4-c531-4989-ba7e-1bea6b18a905">
      <annotation></annotation>
      <assignFromContext>true</assignFromContext>
      <assignToContext>true</assignToContext>
      <inputType>STRING</inputType>
      <isList>false</isList>
      <required>true</required>
      <isPersisted>true</isPersisted>
      <inputSymbol>location</inputSymbol>
      <listDelimiter>,</listDelimiter>
      <record>false</record>
      <prompt></prompt>
      <isMultiSelect>false</isMultiSelect>
      <sourceDelimiter>|</sourceDelimiter>
    </userInputBinding>
  </inputs>
  <possibleResponses>
    <opResponse id="7e27903f-e466-47dd-a9a0-5dec15fed62e">
      <annotation></annotation>
      <name>failure</name>
      <isDefault>false</isDefault>
      <onFailure>true</onFailure>
      <type>ERROR</type>
      <matchRules/>
    </opResponse>
    <opResponse id="5b36edbe-ac22-434e-8179-c004c9a2dd23">
      <annotation></annotation>
      <name>success</name>
      <isDefault>true</isDefault>
      <onFailure>false</onFailure>
      <type>RESOLVED</type>
      <matchRules/>
    </opResponse>
  </possibleResponses>
  <availableResultExpressions/>
  <resultExpression id="46f731d6-c99d-447c-8c54-79653215d555">
    <annotation></annotation>
    <name>FailureMessage</name>
    <fieldName>FailureMessage</fieldName>
    <sourceType>RAWRESULT</sourceType>
    <filters/>
  </resultExpression>
  <iconSpec id="8f1b8cd6-059f-4b25-a588-845c909ec3c7">
    <baseIcon>flow.png</baseIcon>
    <basePath>System</basePath>
    <readOnly>false</readOnly>
    <layers/>
  </iconSpec>
  <callouts/>
  <checkPointFlow>true</checkPointFlow>
  <compatibleRuntimeContext>false</compatibleRuntimeContext>
  <historyCheckPointFlow>true</historyCheckPointFlow>
  <steps>
    <step id="b199c045-0b98-4de0-977c-c0fc0ba4c6f9">
      <annotation></annotation>
      <name>Azure Get auth token</name>
      <bounds>
        <x>0.0</x>
        <y>0.0</y>
      </bounds>
      <layer>-1</layer>
      <hideInbound>false</hideInbound>
      <addResultToRunContext>false</addResultToRunContext>
      <isCriticalStep>false</isCriticalStep>
      <isNonBlocking>false</isNonBlocking>
      <isParallelStep>false</isParallelStep>
      <isSingleResponse>false</isSingleResponse>
      <recordInHistory>false</recordInHistory>
      <recordRawOutput>true</recordRawOutput>
      <recordPrimaryOutput>true</recordPrimaryOutput>
      <checkPointStep>true</checkPointStep>
      <historyCheckPointStep>true</historyCheckPointStep>
      <scriptResultStep>false</scriptResultStep>
      <userPrompt></userPrompt>
      <bindings>
        <userInputBinding id="ca1915ea-2a34-4954-adcf-ebd4df8ab32e">
          <annotation></annotation>
          <assignFromContext>true</assignFromContext>
          <assignToContext>true</assignToContext>
          <inputType>STRING</inputType>
          <isList>false</isList>
          <required>true</required>
          <isPersisted>true</isPersisted>
          <inputSymbol>filePath</inputSymbol>
          <listDelimiter>,</listDelimiter>
          <record>false</record>
          <prompt>fa7a1bdd-c1fa-4188-a856-79c8a0805237.ca1915ea-2a34-4954-adcf-ebd4df8ab32e.prompt</prompt>
          <isMultiSelect>false</isMultiSelect>
          <sourceDelimiter>|</sourceDelimiter>
        </userInputBinding>
        <userInputBinding id="c9558c15-dcb4-4c8c-970e-dfdcf9364d25">
          <annotation></annotation>
          <assignFromContext>true</assignFromContext>
          <assignToContext>true</assignToContext>
          <inputType>STRING</inputType>
          <isList>false</isList>
          <required>true</required>
          <isPersisted>true</isPersisted>
          <inputSymbol>username</inputSymbol>
          <listDelimiter>,</listDelimiter>
          <record>false</record>
          <prompt>fa7a1bdd-c1fa-4188-a856-79c8a0805237.c9558c15-dcb4-4c8c-970e-dfdcf9364d25.prompt</prompt>
          <isMultiSelect>false</isMultiSelect>
          <sourceDelimiter>|</sourceDelimiter>
        </userInputBinding>
        <userInputBinding id="615e6c48-817c-4f92-97ae-a3c180e9e8f8">
          <annotation></annotation>
          <assignFromContext>true</assignFromContext>
          <assignToContext>true</assignToContext>
          <inputType>STRING</inputType>
          <isList>false</isList>
          <required>true</required>
          <isPersisted>true</isPersisted>
          <inputSymbol>password</inputSymbol>
          <listDelimiter>,</listDelimiter>
          <record>false</record>
          <prompt>fa7a1bdd-c1fa-4188-a856-79c8a0805237.615e6c48-817c-4f92-97ae-a3c180e9e8f8.prompt</prompt>
          <isMultiSelect>false</isMultiSelect>
          <sourceDelimiter>|</sourceDelimiter>
        </userInputBinding>
        <staticBinding id="bbe15c2c-ff67-416d-8a52-59de1bd8be2b">
          <annotation></annotation>
          <assignFromContext>true</assignFromContext>
          <assignToContext>true</assignToContext>
          <inputType>STRING</inputType>
          <isList>false</isList>
          <required>false</required>
          <isPersisted>true</isPersisted>
          <inputSymbol>proxyHost</inputSymbol>
          <listDelimiter>,</listDelimiter>
          <value></value>
          <record>false</record>
        </staticBinding>
        <staticBinding id="47cc9762-833e-49e5-b692-294a29dbae33">
          <annotation></annotation>
          <assignFromContext>true</assignFromContext>
          <assignToContext>true</assignToContext>
          <inputType>STRING</inputType>
          <isList>false</isList>
          <required>false</required>
          <isPersisted>true</isPersisted>
          <inputSymbol>proxyPort</inputSymbol>
          <listDelimiter>,</listDelimiter>
          <value></value>
          <record>false</record>
        </staticBinding>
        <staticBinding id="6293df74-f070-4a19-88f6-ea869c8bc8a4">
          <annotation></annotation>
          <assignFromContext>true</assignFromContext>
          <assignToContext>true</assignToContext>
          <inputType>STRING</inputType>
          <isList>false</isList>
          <required>false</required>
          <isPersisted>true</isPersisted>
          <inputSymbol>proxyUsername</inputSymbol>
          <listDelimiter>,</listDelimiter>
          <value></value>
          <record>false</record>
        </staticBinding>
        <staticBinding id="16ad1836-8bec-4ac1-a00b-43ae0ecc6d3a">
          <annotation></annotation>
          <assignFromContext>true</assignFromContext>
          <assignToContext>true</assignToContext>
          <inputType>STRING</inputType>
          <isList>false</isList>
          <required>false</required>
          <isPersisted>true</isPersisted>
          <inputSymbol>proxyPassword</inputSymbol>
          <listDelimiter>,</listDelimiter>
          <value></value>
          <record>false</record>
        </staticBinding>
      </bindings>
      <transitions>
        <transition id="da0a4bed-f1c1-4618-8d59-75bdb4fac7e1">
          <annotation></annotation>
          <name>failure</name>
          <command>NEXT</command>
          <linkMode>false</linkMode>
          <responseSymbol>failure</responseSymbol>
          <shouldHandoff>false</shouldHandoff>
          <transitionValue>0.0</transitionValue>
          <destination>
            <refId>b0e517f3-8054-4156-bf27-3c8bfbcea5f7</refId>
          </destination>
          <source>
            <refId>b199c045-0b98-4de0-977c-c0fc0ba4c6f9</refId>
          </source>
          <positions>
            <point>
              <x>111.0</x>
              <y>97.0</y>
            </point>
            <point>
              <x>271.0</x>
              <y>361.0</y>
            </point>
          </positions>
          <labelPosition>
            <x>333.0</x>
            <y>0.0</y>
          </labelPosition>
        </transition>
        <transition id="bfb262fe-31c4-4d03-8232-1202353fe1df">
          <annotation></annotation>
          <name>success</name>
          <command>NEXT</command>
          <linkMode>false</linkMode>
          <responseSymbol>success</responseSymbol>
          <shouldHandoff>false</shouldHandoff>
          <transitionValue>0.0</transitionValue>
          <destination>
            <refId>e7783fd9-6869-423a-9dc7-2c1ee9325247</refId>
          </destination>
          <source>
            <refId>b199c045-0b98-4de0-977c-c0fc0ba4c6f9</refId>
          </source>
          <positions>
            <point>
              <x>111.0</x>
              <y>97.0</y>
            </point>
            <point>
              <x>268.0</x>
              <y>84.0</y>
            </point>
          </positions>
          <labelPosition>
            <x>333.0</x>
            <y>0.0</y>
          </labelPosition>
        </transition>
      </transitions>
      <properties/>
      <opRef>
        <refId>732a7952-7643-4321-b645-ecc04b415ab2</refId>
      </opRef>
      <assignments>
        <flowVariableAssignment id="8a86bf15-e7f1-4498-8899-296aab2c0823">
          <annotation></annotation>
          <name>assignment</name>
          <action>OVERWRITE</action>
          <assignmentTargetType>FLOW_VARIABLE</assignmentTargetType>
          <contextKey>authToken</contextKey>
          <expression id="2bd5a230-8a70-49e1-8251-1df3f082bc18">
            <annotation></annotation>
            <name>Result Field: returnResult</name>
            <fieldName>returnResult</fieldName>
            <sourceType>RAWRESULT</sourceType>
            <filters/>
          </expression>
        </flowVariableAssignment>
      </assignments>
      <throttleSize>0</throttleSize>
    </step>
    <returnStep id="ee63af37-c96e-4ebb-93eb-2829c082518e">
      <annotation></annotation>
      <name>Resolved : success</name>
      <bounds>
        <x>674.0</x>
        <y>0.0</y>
      </bounds>
      <layer>-1</layer>
      <hideInbound>false</hideInbound>
      <addResultToRunContext>false</addResultToRunContext>
      <isCriticalStep>false</isCriticalStep>
      <isNonBlocking>false</isNonBlocking>
      <isParallelStep>false</isParallelStep>
      <isSingleResponse>false</isSingleResponse>
      <recordInHistory>false</recordInHistory>
      <recordRawOutput>true</recordRawOutput>
      <recordPrimaryOutput>true</recordPrimaryOutput>
      <checkPointStep>true</checkPointStep>
      <historyCheckPointStep>true</historyCheckPointStep>
      <scriptResultStep>false</scriptResultStep>
      <userPrompt></userPrompt>
      <bindings/>
      <transitions>
        <transition id="7b757695-650a-4f1f-a01d-c1dc22136ba9">
          <annotation></annotation>
          <name>return</name>
          <command>NEXT</command>
          <linkMode>false</linkMode>
          <responseSymbol>success</responseSymbol>
          <shouldHandoff>false</shouldHandoff>
          <transitionValue>0.0</transitionValue>
          <destination>
            <refId>ee63af37-c96e-4ebb-93eb-2829c082518e</refId>
          </destination>
          <source>
            <refId>ee63af37-c96e-4ebb-93eb-2829c082518e</refId>
          </source>
          <positions/>
        </transition>
      </transitions>
      <properties/>
      <returnStepType>RESOLVED</returnStepType>
      <assignments/>
    </returnStep>
    <step id="a2fb8a56-43ce-4af6-b407-67cf19ac5b4c">
      <annotation>fa7a1bdd-c1fa-4188-a856-79c8a0805237.a2fb8a56-43ce-4af6-b407-67cf19ac5b4c.description</annotation>
      <name>Get Value from Object</name>
      <bounds>
        <x>430.0</x>
        <y>0.0</y>
      </bounds>
      <layer>-1</layer>
      <hideInbound>false</hideInbound>
      <addResultToRunContext>false</addResultToRunContext>
      <isCriticalStep>false</isCriticalStep>
      <isNonBlocking>false</isNonBlocking>
      <isParallelStep>false</isParallelStep>
      <isSingleResponse>false</isSingleResponse>
      <recordInHistory>false</recordInHistory>
      <recordRawOutput>true</recordRawOutput>
      <recordPrimaryOutput>true</recordPrimaryOutput>
      <checkPointStep>true</checkPointStep>
      <historyCheckPointStep>true</historyCheckPointStep>
      <scriptResultStep>false</scriptResultStep>
      <userPrompt></userPrompt>
      <bindings>
        <staticBinding id="59d35182-e93c-46bc-9880-fbcf18e7932e">
          <annotation></annotation>
          <assignFromContext>false</assignFromContext>
          <assignToContext>true</assignToContext>
          <inputType>STRING</inputType>
          <isList>false</isList>
          <required>true</required>
          <isPersisted>true</isPersisted>
          <inputSymbol>object</inputSymbol>
          <listDelimiter>,</listDelimiter>
          <value>${returnResult}</value>
          <record>false</record>
        </staticBinding>
        <staticBinding id="313c934c-28f9-4ecd-b54d-c5c171e37bcf">
          <annotation></annotation>
          <assignFromContext>false</assignFromContext>
          <assignToContext>true</assignToContext>
          <inputType>STRING</inputType>
          <isList>false</isList>
          <required>true</required>
          <isPersisted>true</isPersisted>
          <inputSymbol>key</inputSymbol>
          <listDelimiter>,</listDelimiter>
          <value>properties.provisioningState</value>
          <record>false</record>
        </staticBinding>
      </bindings>
      <transitions>
        <transition id="e6f40335-14fd-445f-b4c3-d0a71e117bd9">
          <annotation></annotation>
          <name>success</name>
          <command>NEXT</command>
          <linkMode>false</linkMode>
          <responseSymbol>success</responseSymbol>
          <shouldHandoff>false</shouldHandoff>
          <transitionValue>0.0</transitionValue>
          <destination>
            <refId>d7b9e0d1-2db9-41ef-9366-d058ed9a3a07</refId>
          </destination>
          <source>
            <refId>a2fb8a56-43ce-4af6-b407-67cf19ac5b4c</refId>
          </source>
          <positions>
            <point>
              <x>422.0</x>
              <y>97.0</y>
            </point>
            <point>
              <x>588.0</x>
              <y>97.0</y>
            </point>
          </positions>
          <labelPosition>
            <x>333.0</x>
            <y>0.0</y>
          </labelPosition>
        </transition>
        <transition id="edd7d3c9-a2a8-4827-8f6f-120e2fb677da">
          <annotation></annotation>
          <name>failure</name>
          <command>NEXT</command>
          <linkMode>false</linkMode>
          <responseSymbol>failure</responseSymbol>
          <shouldHandoff>false</shouldHandoff>
          <transitionValue>0.0</transitionValue>
          <destination>
            <refId>b0e517f3-8054-4156-bf27-3c8bfbcea5f7</refId>
          </destination>
          <source>
            <refId>a2fb8a56-43ce-4af6-b407-67cf19ac5b4c</refId>
          </source>
          <positions>
            <point>
              <x>422.0</x>
              <y>97.0</y>
            </point>
            <point>
              <x>271.0</x>
              <y>361.0</y>
            </point>
          </positions>
          <labelPosition>
            <x>333.0</x>
            <y>0.0</y>
          </labelPosition>
        </transition>
      </transitions>
      <properties/>
      <opRef>
        <refId>61fc6fd2-7d5c-4d5c-aaa9-71c8250310f2</refId>
      </opRef>
      <assignments>
        <flowVariableAssignment id="6ae2b9ac-b995-4bd5-81f1-cb4a8da88956">
          <annotation></annotation>
          <name>assignment</name>
          <action>OVERWRITE</action>
          <assignmentTargetType>FLOW_VARIABLE</assignmentTargetType>
          <contextKey>state</contextKey>
          <expression id="fc7f2e88-5cdb-4f69-bddf-02bb8ea818ec">
            <annotation></annotation>
            <name>Result Field: Result</name>
            <fieldName>Result</fieldName>
            <sourceType>RAWRESULT</sourceType>
            <filters/>
          </expression>
        </flowVariableAssignment>
      </assignments>
      <throttleSize>0</throttleSize>
    </step>
    <step id="58bd65b6-a38a-41cc-bdc3-4971eb45be16">
      <annotation></annotation>
      <name>Get information about a virtual network</name>
      <bounds>
        <x>300.0</x>
        <y>0.0</y>
      </bounds>
      <layer>-1</layer>
      <hideInbound>false</hideInbound>
      <addResultToRunContext>false</addResultToRunContext>
      <isCriticalStep>false</isCriticalStep>
      <isNonBlocking>false</isNonBlocking>
      <isParallelStep>false</isParallelStep>
      <isSingleResponse>false</isSingleResponse>
      <recordInHistory>false</recordInHistory>
      <recordRawOutput>true</recordRawOutput>
      <recordPrimaryOutput>true</recordPrimaryOutput>
      <checkPointStep>true</checkPointStep>
      <historyCheckPointStep>true</historyCheckPointStep>
      <scriptResultStep>false</scriptResultStep>
      <userPrompt></userPrompt>
      <bindings>
        <userInputBinding id="3a459d9b-9a3c-4e76-9d83-9c045fbf547e">
          <annotation></annotation>
          <assignFromContext>true</assignFromContext>
          <assignToContext>true</assignToContext>
          <inputType>STRING</inputType>
          <isList>false</isList>
          <required>true</required>
          <isPersisted>true</isPersisted>
          <inputSymbol>subscriptionId</inputSymbol>
          <listDelimiter>,</listDelimiter>
          <record>false</record>
          <prompt></prompt>
          <isMultiSelect>false</isMultiSelect>
          <sourceDelimiter>|</sourceDelimiter>
        </userInputBinding>
        <userInputBinding id="47fca533-fd53-4fd9-853a-38d733ae99ab">
          <annotation></annotation>
          <assignFromContext>true</assignFromContext>
          <assignToContext>true</assignToContext>
          <inputType>STRING</inputType>
          <isList>false</isList>
          <required>true</required>
          <isPersisted>true</isPersisted>
          <inputSymbol>resourceGroupName</inputSymbol>
          <listDelimiter>,</listDelimiter>
          <record>false</record>
          <prompt></prompt>
          <isMultiSelect>false</isMultiSelect>
          <sourceDelimiter>|</sourceDelimiter>
        </userInputBinding>
        <userInputBinding id="7bf46aab-6e38-40fb-997a-2cf900e8b24c">
          <annotation></annotation>
          <assignFromContext>true</assignFromContext>
          <assignToContext>true</assignToContext>
          <inputType>STRING</inputType>
          <isList>false</isList>
          <required>true</required>
          <isPersisted>true</isPersisted>
          <inputSymbol>virtualNetworkName</inputSymbol>
          <listDelimiter>,</listDelimiter>
          <record>false</record>
          <prompt></prompt>
          <isMultiSelect>false</isMultiSelect>
          <sourceDelimiter>|</sourceDelimiter>
        </userInputBinding>
        <userInputBinding id="ba1b0271-9684-40de-8313-6fedb01f8827">
          <annotation></annotation>
          <assignFromContext>true</assignFromContext>
          <assignToContext>true</assignToContext>
          <inputType>STRING</inputType>
          <isList>false</isList>
          <required>true</required>
          <isPersisted>true</isPersisted>
          <inputSymbol>authToken</inputSymbol>
          <listDelimiter>,</listDelimiter>
          <record>false</record>
          <prompt></prompt>
          <isMultiSelect>false</isMultiSelect>
          <sourceDelimiter>|</sourceDelimiter>
        </userInputBinding>
        <userInputBinding id="a89e9133-a710-424a-a07d-083da0df3b8c">
          <annotation></annotation>
          <assignFromContext>true</assignFromContext>
          <assignToContext>false</assignToContext>
          <inputType>STRING</inputType>
          <isList>false</isList>
          <required>false</required>
          <isPersisted>true</isPersisted>
          <inputSymbol>proxyHost</inputSymbol>
          <listDelimiter>,</listDelimiter>
          <record>false</record>
          <prompt></prompt>
          <isMultiSelect>false</isMultiSelect>
          <sourceDelimiter>|</sourceDelimiter>
        </userInputBinding>
        <userInputBinding id="9cbbb1d2-954b-48ba-8509-a691809d02c8">
          <annotation></annotation>
          <assignFromContext>true</assignFromContext>
          <assignToContext>false</assignToContext>
          <inputType>STRING</inputType>
          <isList>false</isList>
          <required>false</required>
          <isPersisted>true</isPersisted>
          <inputSymbol>proxyUsername</inputSymbol>
          <listDelimiter>,</listDelimiter>
          <record>false</record>
          <prompt></prompt>
          <isMultiSelect>false</isMultiSelect>
          <sourceDelimiter>|</sourceDelimiter>
        </userInputBinding>
        <userInputBinding id="c7633b2d-f1e8-4a5a-b3d9-5667bd6f03f5">
          <annotation></annotation>
          <assignFromContext>true</assignFromContext>
          <assignToContext>false</assignToContext>
          <inputType>STRING</inputType>
          <isList>false</isList>
          <required>false</required>
          <isPersisted>true</isPersisted>
          <inputSymbol>proxyPassword</inputSymbol>
          <listDelimiter>,</listDelimiter>
          <record>false</record>
          <prompt></prompt>
          <isMultiSelect>false</isMultiSelect>
          <sourceDelimiter>|</sourceDelimiter>
        </userInputBinding>
        <userInputBinding id="7cec3444-cd69-4ff5-9324-554718a5de85">
          <annotation></annotation>
          <assignFromContext>true</assignFromContext>
          <assignToContext>false</assignToContext>
          <inputType>STRING</inputType>
          <isList>false</isList>
          <required>false</required>
          <isPersisted>true</isPersisted>
          <inputSymbol>proxyPort</inputSymbol>
          <listDelimiter>,</listDelimiter>
          <record>false</record>
          <prompt></prompt>
          <isMultiSelect>false</isMultiSelect>
          <sourceDelimiter>|</sourceDelimiter>
        </userInputBinding>
      </bindings>
      <transitions>
        <transition id="b4bb3ec7-bb9f-41bd-8b0c-383603c45223">
          <annotation></annotation>
          <name>success</name>
          <command>NEXT</command>
          <linkMode>false</linkMode>
          <responseSymbol>success</responseSymbol>
          <shouldHandoff>false</shouldHandoff>
          <transitionValue>0.0</transitionValue>
          <destination>
            <refId>a2fb8a56-43ce-4af6-b407-67cf19ac5b4c</refId>
          </destination>
          <source>
            <refId>58bd65b6-a38a-41cc-bdc3-4971eb45be16</refId>
          </source>
          <positions>
            <point>
              <x>350.0</x>
              <y>40.0</y>
            </point>
            <point>
              <x>478.0</x>
              <y>34.0</y>
            </point>
          </positions>
          <labelPosition>
            <x>333.0</x>
            <y>0.0</y>
          </labelPosition>
        </transition>
        <transition id="d7bc64d0-b6be-4123-8679-6b93ba313a35">
          <annotation></annotation>
          <name>failure</name>
          <command>NEXT</command>
          <linkMode>false</linkMode>
          <responseSymbol>failure</responseSymbol>
          <shouldHandoff>false</shouldHandoff>
          <transitionValue>0.0</transitionValue>
          <destination>
            <refId>b0e517f3-8054-4156-bf27-3c8bfbcea5f7</refId>
          </destination>
          <source>
            <refId>58bd65b6-a38a-41cc-bdc3-4971eb45be16</refId>
          </source>
          <positions>
            <point>
              <x>350.0</x>
              <y>40.0</y>
            </point>
            <point>
              <x>271.0</x>
              <y>361.0</y>
            </point>
          </positions>
          <labelPosition>
            <x>333.0</x>
            <y>0.0</y>
          </labelPosition>
        </transition>
      </transitions>
      <properties/>
      <opRef>
        <refId>46b0edf0-7f1c-4a54-b8c9-9abb80b7700f</refId>
      </opRef>
      <assignments>
        <flowVariableAssignment id="42afd007-efa4-45ab-a05a-071a5331c844">
          <annotation></annotation>
          <name>assignment</name>
          <action>OVERWRITE</action>
          <assignmentTargetType>FLOW_VARIABLE</assignmentTargetType>
          <contextKey>returnResult</contextKey>
          <expression id="ab62dce5-040c-47c6-9256-36ece54ca233">
            <annotation></annotation>
            <name>Result Field: returnResult</name>
            <fieldName>returnResult</fieldName>
            <sourceType>RAWRESULT</sourceType>
            <filters/>
          </expression>
        </flowVariableAssignment>
      </assignments>
      <throttleSize>0</throttleSize>
    </step>
    <step id="d7b9e0d1-2db9-41ef-9366-d058ed9a3a07">
      <annotation>fa7a1bdd-c1fa-4188-a856-79c8a0805237.d7b9e0d1-2db9-41ef-9366-d058ed9a3a07.description</annotation>
      <name>String Equals</name>
      <bounds>
        <x>560.0</x>
        <y>0.0</y>
      </bounds>
      <layer>-1</layer>
      <hideInbound>false</hideInbound>
      <iconSpec id="22bb1992-f5ff-439c-b822-94fce91debc7">
        <baseIcon>compare.png</baseIcon>
        <basePath>Utilities/</basePath>
        <readOnly>false</readOnly>
        <layers/>
      </iconSpec>
      <addResultToRunContext>false</addResultToRunContext>
      <isCriticalStep>false</isCriticalStep>
      <isNonBlocking>false</isNonBlocking>
      <isParallelStep>false</isParallelStep>
      <isSingleResponse>false</isSingleResponse>
      <recordInHistory>false</recordInHistory>
      <recordRawOutput>true</recordRawOutput>
      <recordPrimaryOutput>true</recordPrimaryOutput>
      <checkPointStep>true</checkPointStep>
      <historyCheckPointStep>true</historyCheckPointStep>
      <scriptResultStep>false</scriptResultStep>
      <userPrompt></userPrompt>
      <bindings>
        <staticBinding id="5fb1dc4c-1eab-425e-aef5-387dd58b3b6d">
          <annotation></annotation>
          <assignFromContext>false</assignFromContext>
          <assignToContext>false</assignToContext>
          <inputType>STRING</inputType>
          <isList>false</isList>
          <required>false</required>
          <isPersisted>true</isPersisted>
          <inputSymbol>string1</inputSymbol>
          <listDelimiter>,</listDelimiter>
          <value>${state}</value>
          <record>false</record>
        </staticBinding>
        <staticBinding id="95b5e297-d308-4550-927f-f25e99bd30d3">
          <annotation></annotation>
          <assignFromContext>false</assignFromContext>
          <assignToContext>false</assignToContext>
          <inputType>STRING</inputType>
          <isList>false</isList>
          <required>false</required>
          <isPersisted>true</isPersisted>
          <inputSymbol>string2</inputSymbol>
          <listDelimiter>,</listDelimiter>
          <value>Succeeded</value>
          <record>false</record>
        </staticBinding>
        <staticBinding id="3a4340ac-fc5a-46c4-ada6-93239a8344cb">
          <annotation></annotation>
          <assignFromContext>false</assignFromContext>
          <assignToContext>false</assignToContext>
          <inputType>STRING</inputType>
          <isList>false</isList>
          <required>false</required>
          <isPersisted>true</isPersisted>
          <inputSymbol>ignoreCase</inputSymbol>
          <listDelimiter>,</listDelimiter>
          <value>true</value>
          <record>false</record>
        </staticBinding>
        <staticBinding id="b6c04447-d1df-4f61-ba96-8dd76e12cd76">
          <annotation></annotation>
          <toContextKey></toContextKey>
          <fromContextKey></fromContextKey>
          <assignFromContext>false</assignFromContext>
          <assignToContext>false</assignToContext>
          <inputType>STRING</inputType>
          <recordKey></recordKey>
          <isList>false</isList>
          <required>false</required>
          <isPersisted>true</isPersisted>
          <inputSymbol>Field_4</inputSymbol>
          <listDelimiter></listDelimiter>
          <value>${in4}</value>
          <record>false</record>
        </staticBinding>
        <staticBinding id="07ccec9d-71f0-4ebc-88c2-de53085ad1d5">
          <annotation></annotation>
          <toContextKey></toContextKey>
          <fromContextKey></fromContextKey>
          <assignFromContext>false</assignFromContext>
          <assignToContext>false</assignToContext>
          <inputType>STRING</inputType>
          <recordKey></recordKey>
          <isList>false</isList>
          <required>false</required>
          <isPersisted>true</isPersisted>
          <inputSymbol>Field_3</inputSymbol>
          <listDelimiter></listDelimiter>
          <value>${in3}</value>
          <record>false</record>
        </staticBinding>
        <staticBinding id="e9c8e955-e5ee-4669-ab70-23166067f25b">
          <annotation></annotation>
          <toContextKey></toContextKey>
          <fromContextKey></fromContextKey>
          <assignFromContext>false</assignFromContext>
          <assignToContext>false</assignToContext>
          <inputType>STRING</inputType>
          <recordKey></recordKey>
          <isList>false</isList>
          <required>false</required>
          <isPersisted>true</isPersisted>
          <inputSymbol>Field_1</inputSymbol>
          <listDelimiter></listDelimiter>
          <value>${in1}</value>
          <record>false</record>
        </staticBinding>
        <staticBinding id="84bc4f82-9337-4e77-b0c4-3ff7db7e6924">
          <annotation></annotation>
          <toContextKey></toContextKey>
          <fromContextKey></fromContextKey>
          <assignFromContext>false</assignFromContext>
          <assignToContext>false</assignToContext>
          <inputType>STRING</inputType>
          <recordKey></recordKey>
          <isList>false</isList>
          <required>false</required>
          <isPersisted>true</isPersisted>
          <inputSymbol>Field_2</inputSymbol>
          <listDelimiter></listDelimiter>
          <value>${in2}</value>
          <record>false</record>
        </staticBinding>
      </bindings>
      <transitions>
        <transition id="b53637f3-1baa-4001-968f-ee68fe2d173b">
          <annotation></annotation>
          <name>true</name>
          <command>NEXT</command>
          <linkMode>false</linkMode>
          <responseSymbol>true</responseSymbol>
          <shouldHandoff>false</shouldHandoff>
          <transitionValue>0.0</transitionValue>
          <destination>
            <refId>ee63af37-c96e-4ebb-93eb-2829c082518e</refId>
          </destination>
          <source>
            <refId>d7b9e0d1-2db9-41ef-9366-d058ed9a3a07</refId>
          </source>
          <positions>
            <point>
              <x>588.0</x>
              <y>97.0</y>
            </point>
            <point>
              <x>815.0</x>
              <y>135.0</y>
            </point>
          </positions>
          <labelPosition>
            <x>333.0</x>
            <y>0.0</y>
          </labelPosition>
        </transition>
        <transition id="0d1a537c-4a52-4dfd-bd1c-59b27f0dd6bd">
          <annotation></annotation>
          <name>false</name>
          <command>NEXT</command>
          <linkMode>false</linkMode>
          <responseSymbol>false</responseSymbol>
          <shouldHandoff>false</shouldHandoff>
          <transitionValue>0.0</transitionValue>
          <destination>
            <refId>a73d7279-329d-4d5d-aa92-28841ee7ba35</refId>
          </destination>
          <source>
            <refId>d7b9e0d1-2db9-41ef-9366-d058ed9a3a07</refId>
          </source>
          <positions>
            <point>
              <x>588.0</x>
              <y>97.0</y>
            </point>
            <point>
              <x>554.0</x>
              <y>360.0</y>
            </point>
          </positions>
          <labelPosition>
            <x>333.0</x>
            <y>0.0</y>
          </labelPosition>
        </transition>
      </transitions>
      <properties/>
      <opRef>
        <refId>7c2f47aa-a4b3-4a7d-b3d4-007f285f7d29</refId>
      </opRef>
      <assignments/>
      <throttleSize>0</throttleSize>
    </step>
    <returnStep id="b0e517f3-8054-4156-bf27-3c8bfbcea5f7">
      <annotation></annotation>
      <name>Error : failure</name>
      <bounds>
        <x>221.0</x>
        <y>327.0</y>
      </bounds>
      <layer>-1</layer>
      <hideInbound>false</hideInbound>
      <addResultToRunContext>false</addResultToRunContext>
      <isCriticalStep>false</isCriticalStep>
      <isNonBlocking>false</isNonBlocking>
      <isParallelStep>false</isParallelStep>
      <isSingleResponse>false</isSingleResponse>
      <recordInHistory>false</recordInHistory>
      <recordRawOutput>true</recordRawOutput>
      <recordPrimaryOutput>true</recordPrimaryOutput>
      <checkPointStep>true</checkPointStep>
      <historyCheckPointStep>true</historyCheckPointStep>
      <scriptResultStep>false</scriptResultStep>
      <userPrompt></userPrompt>
      <bindings/>
      <transitions>
        <transition id="73406a21-d3a2-48ef-80c5-06ba5d4b2035">
          <annotation></annotation>
          <name>return</name>
          <command>NEXT</command>
          <linkMode>false</linkMode>
          <responseSymbol>failure</responseSymbol>
          <shouldHandoff>false</shouldHandoff>
          <transitionValue>0.0</transitionValue>
          <destination>
            <refId>b0e517f3-8054-4156-bf27-3c8bfbcea5f7</refId>
          </destination>
          <source>
            <refId>b0e517f3-8054-4156-bf27-3c8bfbcea5f7</refId>
          </source>
          <positions/>
        </transition>
      </transitions>
      <properties/>
      <returnStepType>ERROR</returnStepType>
      <assignments/>
    </returnStep>
    <step id="e7783fd9-6869-423a-9dc7-2c1ee9325247">
      <annotation></annotation>
      <name>Create virtual network</name>
      <bounds>
        <x>146.0</x>
        <y>0.0</y>
      </bounds>
      <layer>-1</layer>
      <hideInbound>false</hideInbound>
      <addResultToRunContext>false</addResultToRunContext>
      <isCriticalStep>false</isCriticalStep>
      <isNonBlocking>false</isNonBlocking>
      <isParallelStep>false</isParallelStep>
      <isSingleResponse>false</isSingleResponse>
      <recordInHistory>false</recordInHistory>
      <recordRawOutput>true</recordRawOutput>
      <recordPrimaryOutput>true</recordPrimaryOutput>
      <checkPointStep>true</checkPointStep>
      <historyCheckPointStep>true</historyCheckPointStep>
      <scriptResultStep>false</scriptResultStep>
      <userPrompt></userPrompt>
      <bindings>
        <userInputBinding id="319ec55e-e6b7-4d28-931c-22da297224fd">
          <annotation></annotation>
          <assignFromContext>true</assignFromContext>
          <assignToContext>true</assignToContext>
          <inputType>STRING</inputType>
          <isList>false</isList>
          <required>true</required>
          <isPersisted>true</isPersisted>
          <inputSymbol>subscriptionId</inputSymbol>
          <listDelimiter>,</listDelimiter>
          <record>false</record>
          <prompt>fa7a1bdd-c1fa-4188-a856-79c8a0805237.319ec55e-e6b7-4d28-931c-22da297224fd.prompt</prompt>
          <isMultiSelect>false</isMultiSelect>
          <sourceDelimiter>|</sourceDelimiter>
        </userInputBinding>
        <userInputBinding id="2d92f873-902d-46fd-8600-b984f816e6a5">
          <annotation></annotation>
          <assignFromContext>true</assignFromContext>
          <assignToContext>true</assignToContext>
          <inputType>STRING</inputType>
          <isList>false</isList>
          <required>true</required>
          <isPersisted>true</isPersisted>
          <inputSymbol>resourceGroupName</inputSymbol>
          <listDelimiter>,</listDelimiter>
          <record>false</record>
          <prompt>fa7a1bdd-c1fa-4188-a856-79c8a0805237.2d92f873-902d-46fd-8600-b984f816e6a5.prompt</prompt>
          <isMultiSelect>false</isMultiSelect>
          <sourceDelimiter>|</sourceDelimiter>
        </userInputBinding>
        <userInputBinding id="57261b5a-f8b5-4d78-aa54-1c794d654e13">
          <annotation></annotation>
          <assignFromContext>true</assignFromContext>
          <assignToContext>true</assignToContext>
          <inputType>STRING</inputType>
          <isList>false</isList>
          <required>true</required>
          <isPersisted>true</isPersisted>
          <inputSymbol>virtualNetworkName</inputSymbol>
          <listDelimiter>,</listDelimiter>
          <record>false</record>
          <prompt>fa7a1bdd-c1fa-4188-a856-79c8a0805237.57261b5a-f8b5-4d78-aa54-1c794d654e13.prompt</prompt>
          <isMultiSelect>false</isMultiSelect>
          <sourceDelimiter>|</sourceDelimiter>
        </userInputBinding>
        <userInputBinding id="53c46ea1-4149-4e7c-8a73-d1a2a06ffb01">
          <annotation></annotation>
          <assignFromContext>true</assignFromContext>
          <assignToContext>true</assignToContext>
          <inputType>STRING</inputType>
          <isList>false</isList>
          <required>true</required>
          <isPersisted>true</isPersisted>
          <inputSymbol>authToken</inputSymbol>
          <listDelimiter>,</listDelimiter>
          <record>false</record>
          <prompt>fa7a1bdd-c1fa-4188-a856-79c8a0805237.53c46ea1-4149-4e7c-8a73-d1a2a06ffb01.prompt</prompt>
          <isMultiSelect>false</isMultiSelect>
          <sourceDelimiter>|</sourceDelimiter>
        </userInputBinding>
        <userInputBinding id="101b404d-80bb-451f-974a-4ce0aba2b56a">
          <annotation></annotation>
          <assignFromContext>true</assignFromContext>
          <assignToContext>true</assignToContext>
          <inputType>STRING</inputType>
          <isList>false</isList>
          <required>true</required>
          <isPersisted>true</isPersisted>
          <inputSymbol>location</inputSymbol>
          <listDelimiter>,</listDelimiter>
          <record>false</record>
          <prompt>fa7a1bdd-c1fa-4188-a856-79c8a0805237.101b404d-80bb-451f-974a-4ce0aba2b56a.prompt</prompt>
          <isMultiSelect>false</isMultiSelect>
          <sourceDelimiter>|</sourceDelimiter>
        </userInputBinding>
        <staticBinding id="2637d05d-c7f2-4712-ad55-b21ddb8edb63">
          <annotation></annotation>
          <assignFromContext>true</assignFromContext>
          <assignToContext>false</assignToContext>
          <inputType>STRING</inputType>
          <isList>false</isList>
          <required>false</required>
          <isPersisted>true</isPersisted>
          <inputSymbol>proxyHost</inputSymbol>
          <listDelimiter>,</listDelimiter>
          <value></value>
          <record>false</record>
        </staticBinding>
        <staticBinding id="27f90011-99c6-4af8-89e2-83c90e8882d1">
          <annotation></annotation>
          <assignFromContext>true</assignFromContext>
          <assignToContext>false</assignToContext>
          <inputType>STRING</inputType>
          <isList>false</isList>
          <required>false</required>
          <isPersisted>true</isPersisted>
          <inputSymbol>proxyPort</inputSymbol>
          <listDelimiter>,</listDelimiter>
          <value></value>
          <record>false</record>
        </staticBinding>
        <staticBinding id="ba57db54-a8e1-4458-bbeb-8fdf80035bed">
          <annotation></annotation>
          <assignFromContext>true</assignFromContext>
          <assignToContext>false</assignToContext>
          <inputType>STRING</inputType>
          <isList>false</isList>
          <required>false</required>
          <isPersisted>true</isPersisted>
          <inputSymbol>proxyUsername</inputSymbol>
          <listDelimiter>,</listDelimiter>
          <value></value>
          <record>false</record>
        </staticBinding>
        <staticBinding id="f2f55e3d-807d-47e1-9586-57fdf6ee5da8">
          <annotation></annotation>
          <assignFromContext>true</assignFromContext>
          <assignToContext>false</assignToContext>
          <inputType>STRING</inputType>
          <isList>false</isList>
          <required>false</required>
          <isPersisted>true</isPersisted>
          <inputSymbol>proxyPassword</inputSymbol>
          <listDelimiter>,</listDelimiter>
          <value></value>
          <record>false</record>
        </staticBinding>
      </bindings>
      <transitions>
        <transition id="3c148df9-5e95-499a-97d7-47a7bd1a8d71">
          <annotation></annotation>
          <name>failure</name>
          <command>NEXT</command>
          <linkMode>false</linkMode>
          <responseSymbol>failure</responseSymbol>
          <shouldHandoff>false</shouldHandoff>
          <transitionValue>0.0</transitionValue>
          <destination>
            <refId>b0e517f3-8054-4156-bf27-3c8bfbcea5f7</refId>
          </destination>
          <source>
            <refId>e7783fd9-6869-423a-9dc7-2c1ee9325247</refId>
          </source>
          <positions>
            <point>
              <x>268.0</x>
              <y>84.0</y>
            </point>
            <point>
              <x>271.0</x>
              <y>361.0</y>
            </point>
          </positions>
          <labelPosition>
            <x>333.0</x>
            <y>0.0</y>
          </labelPosition>
        </transition>
        <transition id="9f366788-5977-4a87-9fe6-f9913651b663">
          <annotation></annotation>
          <name>success</name>
          <command>NEXT</command>
          <linkMode>false</linkMode>
          <responseSymbol>success</responseSymbol>
          <shouldHandoff>false</shouldHandoff>
          <transitionValue>0.0</transitionValue>
          <destination>
            <refId>58bd65b6-a38a-41cc-bdc3-4971eb45be16</refId>
          </destination>
          <source>
            <refId>e7783fd9-6869-423a-9dc7-2c1ee9325247</refId>
          </source>
          <positions>
            <point>
              <x>196.0</x>
              <y>34.0</y>
            </point>
            <point>
              <x>350.0</x>
              <y>40.0</y>
            </point>
          </positions>
          <labelPosition>
            <x>333.0</x>
            <y>0.0</y>
          </labelPosition>
        </transition>
      </transitions>
      <properties/>
      <opRef>
        <refId>d61fbd2a-6ce9-4b5c-891e-74061a744ab9</refId>
      </opRef>
      <assignments>
        <flowVariableAssignment id="ffc9b1aa-1ea4-4968-b049-ed4b99429ef8">
          <annotation></annotation>
          <name>assignment</name>
          <action>OVERWRITE</action>
          <assignmentTargetType>FLOW_OUTPUT_FIELD</assignmentTargetType>
          <contextKey>returnResult</contextKey>
          <expression id="370b695f-982d-4928-b00c-bd926c862050">
            <annotation></annotation>
            <name>Result Field: returnResult</name>
            <fieldName>returnResult</fieldName>
            <sourceType>RAWRESULT</sourceType>
            <filters/>
          </expression>
        </flowVariableAssignment>
      </assignments>
      <throttleSize>0</throttleSize>
    </step>
    <step id="a73d7279-329d-4d5d-aa92-28841ee7ba35">
      <annotation>fa7a1bdd-c1fa-4188-a856-79c8a0805237.a73d7279-329d-4d5d-aa92-28841ee7ba35.description</annotation>
      <name>Counter</name>
      <bounds>
        <x>504.0</x>
        <y>326.0</y>
      </bounds>
      <layer>-1</layer>
      <hideInbound>false</hideInbound>
      <iconSpec id="f1277e7f-e975-470c-bb25-448042f69744">
        <baseIcon>calculator.png</baseIcon>
        <basePath>Others</basePath>
        <readOnly>false</readOnly>
        <layers>
          <iconSpec id="7fc426e5-1032-4c78-8f58-d0d4c69b63fb">
            <baseIcon>iterate.png</baseIcon>
            <basePath>Annotations</basePath>
            <readOnly>false</readOnly>
            <layers/>
          </iconSpec>
        </layers>
      </iconSpec>
      <addResultToRunContext>false</addResultToRunContext>
      <isCriticalStep>false</isCriticalStep>
      <isNonBlocking>false</isNonBlocking>
      <isParallelStep>false</isParallelStep>
      <isSingleResponse>false</isSingleResponse>
      <recordInHistory>false</recordInHistory>
      <recordRawOutput>true</recordRawOutput>
      <recordPrimaryOutput>true</recordPrimaryOutput>
      <checkPointStep>true</checkPointStep>
      <historyCheckPointStep>true</historyCheckPointStep>
      <scriptResultStep>false</scriptResultStep>
      <userPrompt></userPrompt>
      <bindings>
        <staticBinding id="fd9ae3ef-c6e3-4cf0-b0a6-f79e863f7465">
          <annotation></annotation>
          <assignFromContext>false</assignFromContext>
          <assignToContext>true</assignToContext>
          <inputType>STRING</inputType>
          <isList>false</isList>
          <required>true</required>
          <isPersisted>true</isPersisted>
          <inputSymbol>from</inputSymbol>
          <listDelimiter>,</listDelimiter>
          <value>0</value>
          <record>false</record>
        </staticBinding>
        <staticBinding id="3dbdbf92-f997-4992-a9bf-78322cc41926">
          <annotation></annotation>
          <assignFromContext>false</assignFromContext>
          <assignToContext>true</assignToContext>
          <inputType>STRING</inputType>
          <isList>false</isList>
          <required>true</required>
          <isPersisted>true</isPersisted>
          <inputSymbol>to</inputSymbol>
          <listDelimiter>,</listDelimiter>
          <value>30</value>
          <record>false</record>
        </staticBinding>
        <staticBinding id="e3efeec1-381f-45ca-aa9b-a53c533be64f">
          <annotation></annotation>
          <assignFromContext>false</assignFromContext>
          <assignToContext>true</assignToContext>
          <inputType>STRING</inputType>
          <isList>false</isList>
          <required>false</required>
          <isPersisted>true</isPersisted>
          <inputSymbol>incrementBy</inputSymbol>
          <listDelimiter>,</listDelimiter>
          <value>1</value>
          <record>false</record>
        </staticBinding>
        <staticBinding id="fbbdfa5b-3268-4516-8322-ff2c9c15dbd9">
          <annotation></annotation>
          <assignFromContext>false</assignFromContext>
          <assignToContext>true</assignToContext>
          <inputType>STRING</inputType>
          <isList>false</isList>
          <required>false</required>
          <isPersisted>true</isPersisted>
          <inputSymbol>reset</inputSymbol>
          <listDelimiter>,</listDelimiter>
          <value>false</value>
          <record>false</record>
        </staticBinding>
      </bindings>
      <transitions>
        <transition id="222b588b-7857-477c-a3c5-ab52da48797c">
          <annotation></annotation>
          <name>failure</name>
          <command>NEXT</command>
          <linkMode>false</linkMode>
          <responseSymbol>failure</responseSymbol>
          <shouldHandoff>false</shouldHandoff>
          <transitionValue>0.0</transitionValue>
          <destination>
            <refId>b0e517f3-8054-4156-bf27-3c8bfbcea5f7</refId>
          </destination>
          <source>
            <refId>a73d7279-329d-4d5d-aa92-28841ee7ba35</refId>
          </source>
          <positions>
            <point>
              <x>554.0</x>
              <y>360.0</y>
            </point>
            <point>
              <x>494.08871325088177</x>
              <y>385.2118567357687</y>
            </point>
            <point>
              <x>331.0879640913451</x>
              <y>385.7878311144243</y>
            </point>
            <point>
              <x>271.0</x>
              <y>361.0</y>
            </point>
          </positions>
          <labelPosition>
            <x>333.0</x>
            <y>0.0</y>
          </labelPosition>
        </transition>
        <transition id="6b6fc066-0729-4e92-9e13-8494b9deb25b">
          <annotation></annotation>
          <name>no more</name>
          <command>NEXT</command>
          <linkMode>false</linkMode>
          <responseSymbol>no more</responseSymbol>
          <shouldHandoff>false</shouldHandoff>
          <transitionValue>0.0</transitionValue>
          <destination>
            <refId>b0e517f3-8054-4156-bf27-3c8bfbcea5f7</refId>
          </destination>
          <source>
            <refId>a73d7279-329d-4d5d-aa92-28841ee7ba35</refId>
          </source>
          <positions>
            <point>
              <x>554.0</x>
              <y>360.0</y>
            </point>
            <point>
              <x>271.0</x>
              <y>361.0</y>
            </point>
          </positions>
          <labelPosition>
            <x>333.0</x>
            <y>0.0</y>
          </labelPosition>
        </transition>
        <transition id="2932c81f-968d-4713-9e8a-4952be5fa48e">
          <annotation></annotation>
          <name>has more</name>
          <command>NEXT</command>
          <linkMode>false</linkMode>
          <responseSymbol>has more</responseSymbol>
          <shouldHandoff>false</shouldHandoff>
          <transitionValue>0.0</transitionValue>
          <destination>
            <refId>2256df27-62ba-4eed-8f36-5d6ac4f4bb53</refId>
          </destination>
          <source>
            <refId>a73d7279-329d-4d5d-aa92-28841ee7ba35</refId>
          </source>
          <positions>
            <point>
              <x>554.0</x>
              <y>360.0</y>
            </point>
            <point>
              <x>509.0</x>
              <y>227.0</y>
            </point>
          </positions>
          <labelPosition>
            <x>333.0</x>
            <y>0.0</y>
          </labelPosition>
        </transition>
      </transitions>
      <properties/>
      <opRef>
        <refId>c62eeb58-f329-4ae3-b336-54bdc5c9f3d6</refId>
      </opRef>
      <assignments/>
      <throttleSize>0</throttleSize>
    </step>
    <step id="2256df27-62ba-4eed-8f36-5d6ac4f4bb53">
      <annotation>fa7a1bdd-c1fa-4188-a856-79c8a0805237.2256df27-62ba-4eed-8f36-5d6ac4f4bb53.description</annotation>
      <name>Sleep</name>
      <bounds>
        <x>459.0</x>
        <y>193.0</y>
      </bounds>
      <layer>-1</layer>
      <hideInbound>false</hideInbound>
      <iconSpec id="5f0d35d9-6474-4ff2-a237-76c77ca7a86f">
        <baseIcon>hourglass.png</baseIcon>
        <basePath>Utilities</basePath>
        <readOnly>false</readOnly>
        <layers/>
      </iconSpec>
      <addResultToRunContext>false</addResultToRunContext>
      <isCriticalStep>false</isCriticalStep>
      <isNonBlocking>false</isNonBlocking>
      <isParallelStep>false</isParallelStep>
      <isSingleResponse>false</isSingleResponse>
      <recordInHistory>false</recordInHistory>
      <recordRawOutput>true</recordRawOutput>
      <recordPrimaryOutput>true</recordPrimaryOutput>
      <checkPointStep>true</checkPointStep>
      <historyCheckPointStep>true</historyCheckPointStep>
      <scriptResultStep>false</scriptResultStep>
      <userPrompt></userPrompt>
      <bindings>
        <staticBinding id="9af85dab-31cd-4b99-9369-571f6cc2dc98">
          <annotation></annotation>
          <assignFromContext>false</assignFromContext>
          <assignToContext>true</assignToContext>
          <inputType>STRING</inputType>
          <isList>false</isList>
          <required>true</required>
          <isPersisted>true</isPersisted>
          <inputSymbol>seconds</inputSymbol>
          <listDelimiter>,</listDelimiter>
          <value>30</value>
          <record>false</record>
        </staticBinding>
        <staticBinding id="5edcbd80-7b6c-43b3-bd71-0a194d9eb75c">
          <annotation></annotation>
          <toContextKey></toContextKey>
          <fromContextKey></fromContextKey>
          <assignFromContext>false</assignFromContext>
          <assignToContext>false</assignToContext>
          <inputType>STRING</inputType>
          <recordKey></recordKey>
          <isList>false</isList>
          <required>false</required>
          <isPersisted>true</isPersisted>
          <inputSymbol>from</inputSymbol>
          <listDelimiter></listDelimiter>
          <value>${from}</value>
          <record>false</record>
        </staticBinding>
        <staticBinding id="55951298-807b-4740-9f44-22a0ca9ab13b">
          <annotation></annotation>
          <toContextKey></toContextKey>
          <fromContextKey></fromContextKey>
          <assignFromContext>false</assignFromContext>
          <assignToContext>false</assignToContext>
          <inputType>STRING</inputType>
          <recordKey></recordKey>
          <isList>false</isList>
          <required>false</required>
          <isPersisted>true</isPersisted>
          <inputSymbol>to</inputSymbol>
          <listDelimiter></listDelimiter>
          <value>${to}</value>
          <record>false</record>
        </staticBinding>
      </bindings>
      <transitions>
        <transition id="f55c96f9-675c-44a0-89ca-d1f8384d0504">
          <annotation></annotation>
          <name>failure</name>
          <command>NEXT</command>
          <linkMode>false</linkMode>
          <responseSymbol>failure</responseSymbol>
          <shouldHandoff>false</shouldHandoff>
          <transitionValue>0.0</transitionValue>
          <destination>
            <refId>b0e517f3-8054-4156-bf27-3c8bfbcea5f7</refId>
          </destination>
          <source>
            <refId>2256df27-62ba-4eed-8f36-5d6ac4f4bb53</refId>
          </source>
          <positions>
            <point>
              <x>509.0</x>
              <y>227.0</y>
            </point>
            <point>
              <x>271.0</x>
              <y>361.0</y>
            </point>
          </positions>
          <labelPosition>
            <x>333.0</x>
            <y>0.0</y>
          </labelPosition>
        </transition>
        <transition id="bdc8ac5f-2c24-4c2f-82c1-12621d0f3c4e">
          <annotation></annotation>
          <name>success</name>
          <command>NEXT</command>
          <linkMode>false</linkMode>
          <responseSymbol>success</responseSymbol>
          <shouldHandoff>false</shouldHandoff>
          <transitionValue>0.0</transitionValue>
          <destination>
            <refId>58bd65b6-a38a-41cc-bdc3-4971eb45be16</refId>
          </destination>
          <source>
            <refId>2256df27-62ba-4eed-8f36-5d6ac4f4bb53</refId>
          </source>
          <positions>
            <point>
              <x>509.0</x>
              <y>227.0</y>
            </point>
            <point>
              <x>350.0</x>
              <y>40.0</y>
            </point>
          </positions>
          <labelPosition>
            <x>333.0</x>
            <y>0.0</y>
          </labelPosition>
        </transition>
      </transitions>
      <properties/>
      <opRef>
        <refId>d1bbf441-824a-450e-afae-2ddec0e0f35e</refId>
      </opRef>
      <assignments/>
      <throttleSize>0</throttleSize>
    </step>
  </steps>
  <startSteps>b199c045-0b98-4de0-977c-c0fc0ba4c6f9</startSteps>
</flow>